async_fs.cpython-311-i386-linux-musl.so
async_fs-0.0.1.dist-info/LICENSE
async_fs-0.0.1.dist-info/WHEEL
async_fs-0.0.1.dist-info/RECORD
async_fs-0.0.1.dist-info/METADATA
async_fs-0.0.1.dist-info/top_level.txt
async_fs.libs/libgcc_s-f3fb5a36.so.1
async_fs.libs/libstdc++-d2a021ba.so.6.0.32
async_fs.libs/liburing-190c17f5.so.2.0.0
