Metadata-Version: 2.1
Name: async-fs
Version: 0.0.1
Summary: Asynchronous file system operations using io_uring
Home-page: https://github.com/DdoSseRr/async_fs
Author: DdoSseRr
Author-email: ddosserr.developer.666@gmail.com
License: MIT
Platform: Linux
Classifier: Programming Language :: Python :: 3.12
Classifier: Programming Language :: C++
Classifier: License :: OSI Approved :: MIT License
Classifier: Operating System :: POSIX :: Linux
Classifier: Operating System :: Unix
Requires-Python: >=3.11
License-File: LICENSE
